batch_queue2/__init__.py
batch_queue2/batch_queue.py
batch_queue2/server.py
batch_queue2-1.0.12.dist-info/LICENSE
batch_queue2-1.0.12.dist-info/METADATA
batch_queue2-1.0.12.dist-info/WHEEL
batch_queue2-1.0.12.dist-info/entry_points.txt
batch_queue2-1.0.12.dist-info/top_level.txt
batch_queue2-1.0.12.dist-info/RECORD
