Metadata-Version: 2.1
Name: batch_queue2
Version: 1.0.12
Summary: A batch queue system implemented with asyncio
Home-page: https://sr.ht/~ndbecker2/batch_queue2/
Author: Neal Becker
Author-email: Neal Becker <ndbecker2@gmail.com>
License: MIT
Project-URL: Repository, https://hg.sr.ht/~ndbecker2/batch_queue2
Keywords: queue,asyncio,batch
Classifier: Programming Language :: Python :: 3
Classifier: License :: OSI Approved :: MIT License
Classifier: Operating System :: OS Independent
Requires-Python: >=3.6
License-File: LICENSE
Requires-Dist: aiohttp
Requires-Dist: pytest
Requires-Dist: pytest-cov
Provides-Extra: testing
Requires-Dist: pytest; extra == "testing"
Requires-Dist: pytest-cov; extra == "testing"
